nmagents/__init__.py
nmagents/command.py
nmagents/utils.py
nmagents-0.1.1.dist-info/METADATA
nmagents-0.1.1.dist-info/WHEEL
nmagents-0.1.1.dist-info/top_level.txt
nmagents-0.1.1.dist-info/RECORD
