Metadata-Version: 2.4
Name: nmagents
Version: 0.1.1
Summary: A Python package for No More Agents project.
Author: Alex Punnen
Author-email: Alex Punnen <your.email@example.com>
Classifier: Programming Language :: Python :: 3
Classifier: Operating System :: OS Independent
Requires-Python: >=3.10
Dynamic: author
Dynamic: requires-python
